{
    "neoforge:conditions": [
        {
            "type": "neoforge:mod_loaded",
            "modid": "ars_nouveau"
        },
        {
            "type": "neoforge:not",
            "value": {
                "type": "neoforge:tag_empty",
                "registry": "minecraft:block",
                "tag": "c:ores/almandine"
            }
        },
        {
            "type": "neoforge:not",
            "value": {
                "type": "neoforge:tag_empty",
                "registry": "minecraft:item",
                "tag": "c:ores/almandine"
            }
        }
    ],

    "type": "ars_nouveau:scry_ritual",
    "augment": "c:ores/almandine",
    "highlight": "c:ores/almandine"
}